_ACTIONet.cpython-38-x86_64-linux-gnu.so
ACTIONet-0.4.1.dist-info/WHEEL
ACTIONet-0.4.1.dist-info/RECORD
ACTIONet-0.4.1.dist-info/top_level.txt
ACTIONet-0.4.1.dist-info/METADATA
ACTIONet.libs/libopenblasp-r0-164709ac.2.20.so
ACTIONet.libs/libblas-c3fa2def.so.3
ACTIONet.libs/libmkl_intel_lp64-0f5f26a2.so.2
ACTIONet.libs/libcolamd-df81802a.so.2.9.6
ACTIONet.libs/libsuitesparseconfig-8cbb543c.so.5.1.2
ACTIONet.libs/libamd-ee7a1f08.so.2.4.6
ACTIONet.libs/libmetis-32017644.so.5.1.0
ACTIONet.libs/libgfortran-d87b8024.so.4.0.0
ACTIONet.libs/libcamd-8768bbd5.so.2.4.6
ACTIONet.libs/liblapack-7d17f698.so.3
ACTIONet.libs/libcholmod-898f982e.so.3.0.11
ACTIONet.libs/libmkl_core-d9bc3be3.so.2
ACTIONet.libs/libgomp-9eb804f7.so.1.0.0
ACTIONet.libs/libmkl_gnu_thread-d5a4bbce.so.2
ACTIONet.libs/libquadmath-2beb93b5.so.0.0.0
ACTIONet.libs/libccolamd-a2149b82.so.2.9.6
ACTIONet/main.py
ACTIONet/__init__.py
ACTIONet/network/cluster.py
ACTIONet/network/centrality.py
ACTIONet/network/build.py
ACTIONet/network/propagation.py
ACTIONet/network/autocorrelation.py
ACTIONet/network/diffusion.py
ACTIONet/network/layout.py
ACTIONet/network/__init__.py
ACTIONet/preprocessing/filter.py
ACTIONet/preprocessing/reduction.py
ACTIONet/preprocessing/normalization.py
ACTIONet/preprocessing/__init__.py
ACTIONet/tools/utils_internal.py
ACTIONet/tools/utils_public.py
ACTIONet/tools/__init__.py
ACTIONet/postprocessing/clusters.py
ACTIONet/postprocessing/archetypes.py
ACTIONet/postprocessing/genes.py
ACTIONet/postprocessing/cells.py
ACTIONet/postprocessing/__init__.py
ACTIONet/decomposition/actionmr.py
ACTIONet/decomposition/spa.py
ACTIONet/decomposition/aa.py
ACTIONet/decomposition/utils.py
ACTIONet/decomposition/regression.py
ACTIONet/decomposition/__init__.py
ACTIONet/decomposition/action.py
ACTIONet/plotting/palettes.py
ACTIONet/plotting/color.py
ACTIONet/plotting/plot.py
ACTIONet/plotting/utils.py
ACTIONet/plotting/__init__.py
