Metadata-Version: 2.1
Name: ACTIONet
Version: 0.4.1
Summary: ACTIONet single-cell analysis framework
Home-page: https://github.com/shmohammadi86/ACTIONet
Author: Shahin Mohammadi
Author-email: shahin.mohammadi@gmail.com
License: UNKNOWN
Platform: UNKNOWN
Requires-Python: >=3.8
Requires-Dist: adjustText (>=0.7.3)
Requires-Dist: anndata (>=0.8.0)
Requires-Dist: cmake
Requires-Dist: cython
Requires-Dist: h5py (>=3.0)
Requires-Dist: mypy
Requires-Dist: natsort (>=7.0.1)
Requires-Dist: nbsphinx
Requires-Dist: numpy (>=1.19.2)
Requires-Dist: orca
Requires-Dist: pandas (>=1.1.5)
Requires-Dist: plotly
Requires-Dist: scanpy (>=1.9.1)
Requires-Dist: scipy (>=1.5.2)
Requires-Dist: seaborn
Requires-Dist: setuphelpers
Requires-Dist: sphinx
Requires-Dist: sphinx-rtd-theme
Requires-Dist: typing-extensions (>=3.7.4)
